odoo9_addon_account_cutoff_prepaid-9.0.1.0.0.99.dev9-py3.8-nspkg.pth
odoo_addons/account_cutoff_prepaid/README.rst
odoo_addons/account_cutoff_prepaid/__init__.py
odoo_addons/account_cutoff_prepaid/__openerp__.py
odoo_addons/account_cutoff_prepaid/i18n/account_cutoff_prepaid.pot
odoo_addons/account_cutoff_prepaid/i18n/am.po
odoo_addons/account_cutoff_prepaid/i18n/ar.po
odoo_addons/account_cutoff_prepaid/i18n/da.po
odoo_addons/account_cutoff_prepaid/i18n/de.po
odoo_addons/account_cutoff_prepaid/i18n/el_GR.po
odoo_addons/account_cutoff_prepaid/i18n/es.po
odoo_addons/account_cutoff_prepaid/i18n/es_ES.po
odoo_addons/account_cutoff_prepaid/i18n/es_MX.po
odoo_addons/account_cutoff_prepaid/i18n/fi.po
odoo_addons/account_cutoff_prepaid/i18n/fr.po
odoo_addons/account_cutoff_prepaid/i18n/fr_FR.po
odoo_addons/account_cutoff_prepaid/i18n/hr.po
odoo_addons/account_cutoff_prepaid/i18n/hr_HR.po
odoo_addons/account_cutoff_prepaid/i18n/it.po
odoo_addons/account_cutoff_prepaid/i18n/ko_KR.po
odoo_addons/account_cutoff_prepaid/i18n/nb.po
odoo_addons/account_cutoff_prepaid/i18n/nb_NO.po
odoo_addons/account_cutoff_prepaid/i18n/nl.po
odoo_addons/account_cutoff_prepaid/i18n/nl_BE.po
odoo_addons/account_cutoff_prepaid/i18n/pt_BR.po
odoo_addons/account_cutoff_prepaid/i18n/ro.po
odoo_addons/account_cutoff_prepaid/i18n/sk.po
odoo_addons/account_cutoff_prepaid/i18n/sl.po
odoo_addons/account_cutoff_prepaid/i18n/tr.po
odoo_addons/account_cutoff_prepaid/i18n/zh_CN.po
odoo_addons/account_cutoff_prepaid/images/prepaid_revenue_done.jpg
odoo_addons/account_cutoff_prepaid/images/prepaid_revenue_draft.jpg
odoo_addons/account_cutoff_prepaid/images/prepaid_revenue_journal_entry.jpg
odoo_addons/account_cutoff_prepaid/migrations/7.0.0.2/pre-migration.py
odoo_addons/account_cutoff_prepaid/models/__init__.py
odoo_addons/account_cutoff_prepaid/models/account_cutoff.py
odoo_addons/account_cutoff_prepaid/models/company.py
odoo_addons/account_cutoff_prepaid/static/description/icon.png
odoo9_addon_account_cutoff_prepaid-9.0.1.0.0.99.dev9.dist-info/METADATA
odoo9_addon_account_cutoff_prepaid-9.0.1.0.0.99.dev9.dist-info/WHEEL
odoo9_addon_account_cutoff_prepaid-9.0.1.0.0.99.dev9.dist-info/namespace_packages.txt
odoo9_addon_account_cutoff_prepaid-9.0.1.0.0.99.dev9.dist-info/top_level.txt
odoo9_addon_account_cutoff_prepaid-9.0.1.0.0.99.dev9.dist-info/RECORD
